tests/build.py
tests/to_ocl.py
tests/data/test_cql.py
tricc_oo/__init__.py
tricc_oo/converters/__init__.py
tricc_oo/converters/codesystem_to_ocl.py
tricc_oo/converters/cql_to_operation.py
tricc_oo/converters/datadictionnary.py
tricc_oo/converters/drawio_type_map.py
tricc_oo/converters/tricc_to_xls_form.py
tricc_oo/converters/utils.py
tricc_oo/converters/xml_to_tricc.py
tricc_oo/converters/cql/cqlLexer.py
tricc_oo/converters/cql/cqlListener.py
tricc_oo/converters/cql/cqlParser.py
tricc_oo/converters/cql/cqlVisitor.py
tricc_oo/models/__init__.py
tricc_oo/models/base.py
tricc_oo/models/calculate.py
tricc_oo/models/lang.py
tricc_oo/models/ocl.py
tricc_oo/models/ordered_set.py
tricc_oo/models/tricc.py
tricc_oo/parsers/__init__.py
tricc_oo/parsers/xml.py
tricc_oo/serializers/__init__.py
tricc_oo/serializers/planuml.py
tricc_oo/serializers/xls_form.py
tricc_oo/strategies/__init__.py
tricc_oo/strategies/input/__init__.py
tricc_oo/strategies/input/base_input_strategy.py
tricc_oo/strategies/input/drawio.py
tricc_oo/strategies/output/base_output_strategy.py
tricc_oo/strategies/output/dhis2_form.py
tricc_oo/strategies/output/fhir_form.py
tricc_oo/strategies/output/html_form.py
tricc_oo/strategies/output/openmrs_form.py
tricc_oo/strategies/output/spice.py
tricc_oo/strategies/output/xls_form.py
tricc_oo/strategies/output/xlsform_cdss.py
tricc_oo/strategies/output/xlsform_cht.py
tricc_oo/strategies/output/xlsform_cht_hf.py
tricc_oo/visitors/__init__.py
tricc_oo/visitors/tricc.py
tricc_oo/visitors/utils.py
tricc_oo/visitors/xform_pd.py
tricc_oo-1.6.24.dist-info/licenses/LICENSE
tricc_oo-1.6.24.dist-info/METADATA
tricc_oo-1.6.24.dist-info/WHEEL
tricc_oo-1.6.24.dist-info/top_level.txt
tricc_oo-1.6.24.dist-info/RECORD
