Metadata-Version: 2.4
Name: tricc-oo
Version: 1.6.24
Summary: Python library that converts CDSS L2 in L3
Project-URL: Homepage, https://github.com/SwissTPH/tricc
Project-URL: Issues, https://github.com/SwissTPH/tricc/issues
Keywords: xlsform,drawio,authoring
Classifier: Programming Language :: Python :: 3
Classifier: Operating System :: OS Independent
Requires-Python: >=3.8
License-File: LICENSE
Requires-Dist: lxml
Requires-Dist: markdownify
Requires-Dist: pydantic
Requires-Dist: babel
Requires-Dist: xlsxwriter
Requires-Dist: html2text
Requires-Dist: pandas
Requires-Dist: polib
Requires-Dist: strenum
Requires-Dist: fhir.resources
Requires-Dist: antlr4-python3-runtime==4.13.2
Requires-Dist: antlr4-tools==0.2.1
Requires-Dist: beautifulsoup4
Requires-Dist: ocldev
Requires-Dist: pyxform
Dynamic: license-file
